autumn/__init__.py
autumn/client.py
autumn/event_dispatcher.py
autumn/event_queue.py
autumn/executor.py
autumn/exit_state.py
autumn/info_displayer.py
autumn/serializer.py
autumn/subscriber.py
autumn/websocket_server.py
autumn/events/__init__.py
autumn/events/client_disconnected.py
autumn/events/domain_event.py
autumn/events/error_response.py
autumn/events/event.py
autumn/events/notification.py
autumn/events/request.py
autumn/events/response.py
autumn/events/server_disconnect.py
autumn/events/shutdown_requested.py
autumn/handler/__init__.py
autumn/handler/decorators.py
autumn/handler/error_handler.py
autumn/handler/handler.py
autumn/handler/handler_bootstrapper.py
autumn/init/__init__.py
autumn/init/__main__.py
autumn/repository/__init__.py
autumn/repository/memory_repository.py
autumn/repository/memory_repository_factory.py
autumn/repository/mongo_repository.py
autumn/repository/mongo_repository_factory.py
autumn/repository/repository.py
autumn/repository/repository_factory.py
autumn/repository/storable.py
autumn/repository/repository_extension/__init__.py
autumn/repository/repository_extension/decorators.py
autumn/repository/repository_extension/extension.py
autumn/repository/repository_extension/extension_bootstapper.py
autumn/state_machine/__init__.py
autumn/state_machine/state.py
autumn/state_machine/state_configurator.py
autumn/state_machine/state_machine.py
autumn/state_machine/state_machine_builder.py
autumn/store/__init__.py
autumn/store/client_store.py
autumn/store/correlation_store.py
autumn/store/store.py
autumn/store/thread_store.py
autumn/topic/__init__.py
autumn/topic/topic.py
autumn/topic/topic_factory.py
autumn_boot-1.0.4.dist-info/LICENSE
autumn_boot-1.0.4.dist-info/METADATA
autumn_boot-1.0.4.dist-info/WHEEL
autumn_boot-1.0.4.dist-info/top_level.txt
autumn_boot-1.0.4.dist-info/RECORD
